optiflowx/__init__.py
optiflowx/core/__init__.py
optiflowx/core/base_optimizer.py
optiflowx/core/metrics.py
optiflowx/core/model_search_manager.py
optiflowx/core/model_wrapper.py
optiflowx/core/optimization_engine.py
optiflowx/core/optimize_pipeline.py
optiflowx/core/parallel_executor.py
optiflowx/core/pipeline.py
optiflowx/core/search_space.py
optiflowx/models/__init__.py
optiflowx/models/registry.py
optiflowx/models/configs/__init__.py
optiflowx/models/configs/custom_model_config.py
optiflowx/models/configs/decision_tree_config.py
optiflowx/models/configs/knn_config.py
optiflowx/models/configs/linear_regression_config.py
optiflowx/models/configs/logistic_regression_config.py
optiflowx/models/configs/mlp_config.py
optiflowx/models/configs/random_forest_config.py
optiflowx/models/configs/svc_config.py
optiflowx/models/configs/xgboost_config.py
optiflowx/models/wrappers/__init__.py
optiflowx/models/wrappers/custom_model.py
optiflowx/optimizers/__init__.py
optiflowx/optimizers/ant_colony.py
optiflowx/optimizers/bayesian.py
optiflowx/optimizers/genetic.py
optiflowx/optimizers/grey_wolf.py
optiflowx/optimizers/pso.py
optiflowx/optimizers/random_search.py
optiflowx/optimizers/simulated_annealing.py
optiflowx/optimizers/tpe.py
optiflowx/utils/__init__.py
optiflowx/utils/sanitize.py
optiflowx-0.0.9.dist-info/METADATA
optiflowx-0.0.9.dist-info/WHEEL
optiflowx-0.0.9.dist-info/licenses/LICENSE
optiflowx-0.0.9.dist-info/RECORD
