Metadata-Version: 2.4
Name: optiflowx
Version: 0.0.9
Summary: A modular optimization and machine learning workflow framework for hyperparameter tuning and performance benchmarking across diverse datasets.
Project-URL: Homepage, https://github.com/Faycal214/optiflowx
Project-URL: Repository, https://github.com/Faycal214/optiflowx
Project-URL: Issues, https://github.com/Faycal214/optiflowx/issues
Author-email: Alikacem Faycal <faycal213.dz@gmail.com>
License: MIT
License-File: LICENSE
Keywords: AutoML,ant colony optimization,bayesian optimization,combinatorial optimization,genetic algorithm,grey wolf optimization,hyperparameter optimization,machine learning,particle swarm optimization,simulated annealing,tpe
Classifier: License :: OSI Approved :: MIT License
Classifier: Operating System :: OS Independent
Classifier: Programming Language :: Python :: 3
Classifier: Programming Language :: Python :: 3.10
Classifier: Programming Language :: Python :: 3.11
Classifier: Programming Language :: Python :: 3.12
Requires-Python: >=3.10
Requires-Dist: numpy
Requires-Dist: optuna
Requires-Dist: scikit-learn
Requires-Dist: scikit-optimize
Requires-Dist: tqdm
Provides-Extra: dev
Requires-Dist: black>=24.0; extra == 'dev'
Requires-Dist: build; extra == 'dev'
Requires-Dist: mypy>=1.5; extra == 'dev'
Requires-Dist: pytest-cov>=4.0; extra == 'dev'
Requires-Dist: pytest>=7.0; extra == 'dev'
Requires-Dist: ruff>=0.5.0; extra == 'dev'
Requires-Dist: twine; extra == 'dev'
Provides-Extra: docs
Requires-Dist: mkdocs; extra == 'docs'
Requires-Dist: mkdocs-material; extra == 'docs'
Provides-Extra: optuna
Requires-Dist: optuna>=3.0; extra == 'optuna'
Provides-Extra: skopt
Requires-Dist: scikit-optimize>=0.9; extra == 'skopt'
Provides-Extra: xgboost
Requires-Dist: xgboost>=2.0; extra == 'xgboost'
